skvalidate/__init__.py
skvalidate/clang_tidy.py
skvalidate/cli.py
skvalidate/git.py
skvalidate/skvalidate.py
skvalidate/commands/__init__.py
skvalidate/commands/absolute_to_relative_path.py
skvalidate/commands/cpp_check_format.py
skvalidate/commands/detect_software_versions.py
skvalidate/commands/execute.py
skvalidate/commands/file_info.py
skvalidate/commands/get_artifact_url.py
skvalidate/commands/get_target_branch.py
skvalidate/commands/make_demo_report.py
skvalidate/commands/make_report.py
skvalidate/commands/merge_json.py
skvalidate/commands/metric_diff.py
skvalidate/commands/remove_from_env.py
skvalidate/commands/root_diff.py
skvalidate/commands/root_info.py
skvalidate/commands/submit_report_to_mr.py
skvalidate/commands/version.py
skvalidate/compare/__init__.py
skvalidate/compare/metrics.py
skvalidate/data/config/report/demo.yml
skvalidate/data/config/report/gitlab_report.yml
skvalidate/data/examples/file_metrics.json
skvalidate/data/examples/file_metrics_ref.json
skvalidate/data/examples/memory_profile.dat
skvalidate/data/examples/memory_profile_ref.dat
skvalidate/data/examples/performance_metrics.json
skvalidate/data/examples/performance_metrics_ref.json
skvalidate/data/examples/software_versions.json
skvalidate/data/examples/validation.json
skvalidate/data/examples/root_diff/test_1_2/generate.sh
skvalidate/data/examples/root_diff/test_1_2/root_diff.json
skvalidate/data/examples/root_diff/test_1_2/test.a.png
skvalidate/data/examples/root_diff/test_1_2/test.x.png
skvalidate/data/examples/root_diff/test_1_2/test.y.png
skvalidate/data/examples/root_diff/test_1_2/test.z.png
skvalidate/data/examples/root_diff/test_1_3/generate.sh
skvalidate/data/examples/root_diff/test_1_3/root_diff.json
skvalidate/data/examples/root_diff/test_1_3/test.a.png
skvalidate/data/examples/root_diff/test_1_3/test.x.png
skvalidate/data/examples/root_diff/test_1_3/test.y.png
skvalidate/data/examples/root_diff/test_1_3/test.z.png
skvalidate/data/templates/report/default/cpp_check_format.md
scikit_validate-2025.1.1.dist-info/AUTHORS.rst
scikit_validate-2025.1.1.dist-info/LICENSE
scikit_validate-2025.1.1.dist-info/METADATA
scikit_validate-2025.1.1.dist-info/WHEEL
scikit_validate-2025.1.1.dist-info/entry_points.txt
scikit_validate-2025.1.1.dist-info/top_level.txt
scikit_validate-2025.1.1.dist-info/RECORD
