Metadata-Version: 2.2
Name: scikit-validate
Version: 2025.1.1
Summary: Science validation toolkit
Home-page: https://gitlab.cern.ch/fast-hep/public/scikit-validate
Author: Luke Kreczko
Author-email: kreczko@cern.ch
License: Apache Software License 2.0
Keywords: skvalidate
Classifier: Development Status :: 4 - Beta
Classifier: Intended Audience :: Developers
Classifier: License :: OSI Approved :: Apache Software License
Classifier: Natural Language :: English
Classifier: Programming Language :: Python :: 3
Classifier: Programming Language :: Python :: 3.7
Classifier: Programming Language :: Python :: 3.8
Classifier: Programming Language :: Python :: 3.9
License-File: LICENSE
License-File: AUTHORS.rst
Requires-Dist: awkward>=1.0.0
Requires-Dist: Click<9.0
Requires-Dist: gitpython<6.0.0
Requires-Dist: fuzzywuzzy
Requires-Dist: jinja2
Requires-Dist: markdown2
Requires-Dist: matplotlib<4.0.0
Requires-Dist: memory_profiler>=0.54
Requires-Dist: numexpr
Requires-Dist: numpy>=1.19.0
Requires-Dist: pandas
Requires-Dist: plumbum
Requires-Dist: python-gitlab<3.0.0
Requires-Dist: python-Levenshtein
Requires-Dist: pyyaml
Requires-Dist: scipy
Requires-Dist: tabulate
Requires-Dist: tqdm
Requires-Dist: uproot>=4.0.0
Requires-Dist: xhtml2pdf
Provides-Extra: test
Requires-Dist: coverage; extra == "test"
Requires-Dist: httmock; extra == "test"
Requires-Dist: hypothesis; extra == "test"
Requires-Dist: mock; extra == "test"
Requires-Dist: pytest; extra == "test"
Requires-Dist: pytest-cov; extra == "test"
Requires-Dist: responses; extra == "test"
Dynamic: author
Dynamic: author-email
Dynamic: classifier
Dynamic: description
Dynamic: home-page
Dynamic: keywords
Dynamic: license
Dynamic: provides-extra
Dynamic: requires-dist
Dynamic: summary
